{
  "id": "1fa1e77c-6bc1-4aed-a370-402b3b5ecd12",
  "revision": 0,
  "last_node_id": 23,
  "last_link_id": 24,
  "nodes": [
    {
      "id": 2,
      "type": "TaskAgentContextComposerNode",
      "pos": [
        704.1566086994668,
        -629.1948214147495
      ],
      "size": [
        400,
        552
      ],
      "flags": {},
      "order": 6,
      "mode": 0,
      "inputs": [
        {
          "name": "task_bundle_json",
          "type": "STRING",
          "widget": {
            "name": "task_bundle_json"
          },
          "link": 2
        },
        {
          "name": "resource_bundle_json",
          "type": "STRING",
          "widget": {
            "name": "resource_bundle_json"
          },
          "link": 3
        }
      ],
      "outputs": [
        {
          "name": "context_bundle_json",
          "type": "STRING",
          "links": [
            1
          ]
        },
        {
          "name": "status",
          "type": "STRING",
          "links": null
        }
      ],
      "properties": {
        "Node name for S&R": "TaskAgentContextComposerNode"
      },
      "widgets_values": [
        "",
        "",
        "",
        "",
        "",
        "",
        "",
        "",
        "",
        "",
        "",
        ""
      ]
    },
    {
      "id": 3,
      "type": "TaskAgentTaskModuleComposerNode",
      "pos": [
        285.9303817907764,
        -624.3275161049139
      ],
      "size": [
        400,
        360
      ],
      "flags": {},
      "order": 0,
      "mode": 0,
      "inputs": [],
      "outputs": [
        {
          "name": "task_bundle_json",
          "type": "STRING",
          "links": [
            2
          ]
        },
        {
          "name": "status",
          "type": "STRING",
          "links": null
        }
      ],
      "properties": {
        "Node name for S&R": "TaskAgentTaskModuleComposerNode"
      },
      "widgets_values": [
        "translate_anime_tags",
        "expand_anime_tags",
        "normalize_anime_tags",
        "",
        "noobai_xl_1_1",
        "zh_to_en_tags",
        "Danbooru tags; NoobAI XL 1.1; use readable space-separated tags; preserve canonical character tags; put quality tags at the end.",
        "中文描述转 NoobAI XL 1.1 可用英文提示词：先翻译，再扩写，再规格化。适合画图用反推/提示词生成，不是训练打标。",
        ""
      ]
    },
    {
      "id": 10,
      "type": "ShowText|pysssss",
      "pos": [
        1523.809046353785,
        27.464453001578587
      ],
      "size": [
        436.3785749849169,
        471.43387090534225
      ],
      "flags": {},
      "order": 10,
      "mode": 0,
      "inputs": [
        {
          "label": "文本",
          "name": "text",
          "type": "STRING",
          "link": 9
        }
      ],
      "outputs": [
        {
          "label": "字符串",
          "name": "STRING",
          "shape": 6,
          "type": "STRING",
          "links": null
        }
      ],
      "properties": {
        "cnr_id": "comfyui-custom-scripts",
        "ver": "609f3afaa74b2f88ef9ce8d939626065e3247469",
        "Node name for S&R": "ShowText|pysssss"
      },
      "widgets_values": ""
    },
    {
      "id": 12,
      "type": "ShowText|pysssss",
      "pos": [
        1128.0691864935636,
        138.30785417338464
      ],
      "size": [
        379.8667847546428,
        357.03786406789936
      ],
      "flags": {},
      "order": 11,
      "mode": 0,
      "inputs": [
        {
          "label": "文本",
          "name": "text",
          "type": "STRING",
          "link": 11
        }
      ],
      "outputs": [
        {
          "label": "字符串",
          "name": "STRING",
          "shape": 6,
          "type": "STRING",
          "links": null
        }
      ],
      "properties": {
        "cnr_id": "comfyui-custom-scripts",
        "ver": "609f3afaa74b2f88ef9ce8d939626065e3247469",
        "Node name for S&R": "ShowText|pysssss"
      },
      "widgets_values": ""
    },
    {
      "id": 4,
      "type": "TaskAgentResourceLoaderNode",
      "pos": [
        -20.78987459746857,
        -316.9735197498858
      ],
      "size": [
        290,
        214
      ],
      "flags": {},
      "order": 1,
      "mode": 0,
      "inputs": [],
      "outputs": [
        {
          "name": "resource_text",
          "type": "STRING",
          "links": null
        },
        {
          "name": "resource_json",
          "type": "STRING",
          "links": null
        },
        {
          "name": "resource_bundle_json",
          "type": "STRING",
          "links": [
            5
          ]
        },
        {
          "name": "status",
          "type": "STRING",
          "links": null
        }
      ],
      "properties": {
        "Node name for S&R": "TaskAgentResourceLoaderNode"
      },
      "widgets_values": [
        "builtin_catalog",
        "resource::danbooru_character_aliases",
        "",
        "",
        "auto"
      ]
    },
    {
      "id": 14,
      "type": "PromptStudioPositiveOutput",
      "pos": [
        1127.565930791791,
        -805.5697870321521
      ],
      "size": [
        384.26800697020076,
        112
      ],
      "flags": {},
      "order": 2,
      "mode": 0,
      "inputs": [],
      "outputs": [
        {
          "name": "positive",
          "type": "STRING",
          "links": [
            13
          ]
        }
      ],
      "properties": {
        "Node name for S&R": "PromptStudioPositiveOutput"
      },
      "widgets_values": [
        "models/gemma-4-e4b-q4/gemma-4-E4B-it-uncensored-Q4_K_M.gguf",
        ""
      ]
    },
    {
      "id": 16,
      "type": "Note",
      "pos": [
        897.7248343788955,
        -788.2417826548269
      ],
      "size": [
        210,
        88
      ],
      "flags": {},
      "order": 3,
      "mode": 0,
      "inputs": [],
      "outputs": [],
      "properties": {},
      "widgets_values": [
        "可选：默认用 config/backend_profiles.json 的模型路径。只有把标签工具 model_source 改成 custom_path 时，才需要连接并填写这里的 GGUF 模型路径。"
      ],
      "color": "#432",
      "bgcolor": "#653"
    },
    {
      "id": 7,
      "type": "PromptStudioPositiveOutput",
      "pos": [
        706.3877809288914,
        -17.33206104445834
      ],
      "size": [
        400,
        200
      ],
      "flags": {},
      "order": 4,
      "mode": 0,
      "inputs": [],
      "outputs": [
        {
          "name": "positive",
          "type": "STRING",
          "links": [
            6
          ]
        }
      ],
      "properties": {
        "Node name for S&R": "PromptStudioPositiveOutput"
      },
      "widgets_values": [
        "博丽灵梦坐在博丽神社的鸟居前的楼梯上发呆",
        ""
      ]
    },
    {
      "id": 11,
      "type": "ShowText|pysssss",
      "pos": [
        1121.3163209465972,
        -116.06885111904775
      ],
      "size": [
        388.5497612506704,
        188.80549877367275
      ],
      "flags": {},
      "order": 12,
      "mode": 0,
      "inputs": [
        {
          "label": "文本",
          "name": "text",
          "type": "STRING",
          "link": 10
        }
      ],
      "outputs": [
        {
          "label": "字符串",
          "name": "STRING",
          "shape": 6,
          "type": "STRING",
          "links": null
        }
      ],
      "properties": {
        "cnr_id": "comfyui-custom-scripts",
        "ver": "609f3afaa74b2f88ef9ce8d939626065e3247469",
        "Node name for S&R": "ShowText|pysssss"
      },
      "widgets_values": ""
    },
    {
      "id": 5,
      "type": "TaskAgentResourceBundleMergeNode",
      "pos": [
        286.75805123779287,
        -192.87685151492715
      ],
      "size": [
        400,
        270
      ],
      "flags": {},
      "order": 5,
      "mode": 0,
      "inputs": [
        {
          "name": "resource_bundle_json_1",
          "type": "STRING",
          "widget": {
            "name": "resource_bundle_json_1"
          },
          "link": 5
        }
      ],
      "outputs": [
        {
          "name": "resource_bundle_json",
          "type": "STRING",
          "links": [
            3
          ]
        },
        {
          "name": "status",
          "type": "STRING",
          "links": null
        }
      ],
      "properties": {
        "Node name for S&R": "TaskAgentResourceBundleMergeNode"
      },
      "widgets_values": [
        "",
        "",
        "",
        ""
      ]
    },
    {
      "id": 8,
      "type": "ShowText|pysssss",
      "pos": [
        1530.321216620436,
        -627.0137762793238
      ],
      "size": [
        431.9644946779231,
        315.7937878171374
      ],
      "flags": {},
      "order": 8,
      "mode": 0,
      "inputs": [
        {
          "label": "文本",
          "name": "text",
          "type": "STRING",
          "link": 7
        }
      ],
      "outputs": [
        {
          "label": "字符串",
          "name": "STRING",
          "shape": 6,
          "type": "STRING",
          "links": []
        }
      ],
      "properties": {
        "cnr_id": "comfyui-custom-scripts",
        "ver": "609f3afaa74b2f88ef9ce8d939626065e3247469",
        "Node name for S&R": "ShowText|pysssss"
      },
      "widgets_values": ""
    },
    {
      "id": 9,
      "type": "ShowText|pysssss",
      "pos": [
        1527.723593554801,
        -249.73186080280973
      ],
      "size": [
        428.7083847024496,
        217.0250854382458
      ],
      "flags": {},
      "order": 9,
      "mode": 0,
      "inputs": [
        {
          "label": "文本",
          "name": "text",
          "type": "STRING",
          "link": 8
        }
      ],
      "outputs": [
        {
          "label": "字符串",
          "name": "STRING",
          "shape": 6,
          "type": "STRING",
          "links": []
        }
      ],
      "properties": {
        "cnr_id": "comfyui-custom-scripts",
        "ver": "609f3afaa74b2f88ef9ce8d939626065e3247469",
        "Node name for S&R": "ShowText|pysssss"
      },
      "widgets_values": ""
    },
    {
      "id": 1,
      "type": "TaskAgentTagUtilityNode",
      "pos": [
        1115.0529182427567,
        -627.7089760718716
      ],
      "size": [
        400,
        456
      ],
      "flags": {},
      "order": 7,
      "mode": 0,
      "inputs": [
        {
          "name": "context_bundle_json",
          "shape": 7,
          "type": "STRING",
          "link": 1
        },
        {
          "name": "custom_model_path",
          "type": "STRING",
          "widget": {
            "name": "custom_model_path"
          },
          "link": 13
        },
        {
          "name": "text_input",
          "type": "STRING",
          "widget": {
            "name": "text_input"
          },
          "link": 6
        }
      ],
      "outputs": [
        {
          "name": "positive_prompt",
          "type": "STRING",
          "links": [
            7
          ]
        },
        {
          "name": "negative_prompt",
          "type": "STRING",
          "links": [
            8
          ]
        },
        {
          "name": "raw_text",
          "type": "STRING",
          "links": [
            9
          ]
        },
        {
          "name": "json_text",
          "type": "STRING",
          "links": [
            11
          ]
        },
        {
          "name": "status",
          "type": "STRING",
          "links": [
            10
          ]
        }
      ],
      "properties": {
        "Node name for S&R": "TaskAgentTagUtilityNode"
      },
      "widgets_values": [
        "http://127.0.0.1:8765",
        "llama_cpp_python_inproc",
        "profile_catalog",
        "gemma4_e4b_q4 | Gemma 4 E4B Q4",
        "",
        "",
        4096,
        10,
        512,
        0,
        true,
        true,
        "这里可直接输入中文描述；当前示例已连接左侧 Prompt Studio 文本输出。"
      ]
    }
  ],
  "links": [
    [
      1,
      2,
      0,
      1,
      0,
      "STRING"
    ],
    [
      2,
      3,
      0,
      2,
      0,
      "STRING"
    ],
    [
      3,
      5,
      0,
      2,
      1,
      "STRING"
    ],
    [
      5,
      4,
      2,
      5,
      0,
      "STRING"
    ],
    [
      6,
      7,
      0,
      1,
      2,
      "STRING"
    ],
    [
      7,
      1,
      0,
      8,
      0,
      "STRING"
    ],
    [
      8,
      1,
      1,
      9,
      0,
      "STRING"
    ],
    [
      9,
      1,
      2,
      10,
      0,
      "STRING"
    ],
    [
      10,
      1,
      4,
      11,
      0,
      "STRING"
    ],
    [
      11,
      1,
      3,
      12,
      0,
      "STRING"
    ],
    [
      13,
      14,
      0,
      1,
      1,
      "STRING"
    ]
  ],
  "groups": [],
  "config": {},
  "extra": {
    "ds": {
      "scale": 0.6934334949441731,
      "offset": [
        266.16871756274645,
        1411.0346872495045
      ]
    },
    "frontendVersion": "1.42.11"
  },
  "version": 0.4
}
